[
  {
    "id": "opt-door-rollup-rear",
    "optionName": "Roll-Up Door \u2014 Rear",
    "category": "Exterior",
    "compatibleBodies": ["Standard Box"],
    "price": 0,
    "leadTime": 8,
    "weight": { "value": 35, "unit": "lbs" },
    "status": "Active",
    "lastUpdated": "2026-01-15",
    "description": "Aluminum roll-up door on rear of box body. Standard for package delivery applications.",
    "manufacturer": "EAVX"
  },
  {
    "id": "opt-door-swing-rear",
    "optionName": "Swing Doors \u2014 Rear",
    "category": "Exterior",
    "compatibleBodies": ["Standard Box"],
    "price": 200,
    "leadTime": 8,
    "weight": { "value": 40, "unit": "lbs" },
    "status": "Active",
    "lastUpdated": "2026-01-15",
    "description": "Double swing doors on rear. Popular for service body and mixed-use configurations.",
    "manufacturer": "EAVX"
  },
  {
    "id": "opt-door-sliding-side",
    "optionName": "Sliding Door \u2014 Side",
    "category": "Exterior",
    "compatibleBodies": ["Standard Box"],
    "price": 500,
    "leadTime": 10,
    "weight": { "value": 30, "unit": "lbs" },
    "status": "Active",
    "lastUpdated": "2026-01-15",
    "description": "Side sliding door for curbside access.",
    "manufacturer": "EAVX"
  },
  {
    "id": "opt-door-rollup-rear-side",
    "optionName": "Roll-Up Doors \u2014 Rear + Side",
    "category": "Exterior",
    "compatibleBodies": ["Standard Box"],
    "price": 750,
    "leadTime": 10,
    "weight": { "value": 65, "unit": "lbs" },
    "status": "Active",
    "lastUpdated": "2026-01-15",
    "description": "Dual roll-up doors for both rear and side access.",
    "manufacturer": "EAVX"
  },
  {
    "id": "opt-upfit-package-shelving",
    "optionName": "Package Delivery Shelving",
    "category": "Interior",
    "compatibleBodies": ["Standard Box"],
    "price": 2500,
    "leadTime": 8,
    "weight": { "value": 75, "unit": "lbs" },
    "status": "Active",
    "lastUpdated": "2026-01-15",
    "description": "Modular shelf system designed for parcel sorting and delivery. Multiple shelf tiers with adjustable dividers.",
    "manufacturer": "EAVX"
  },
  {
    "id": "opt-upfit-service-workbench",
    "optionName": "Service Body Workbench",
    "category": "Interior",
    "compatibleBodies": ["Standard Box"],
    "price": 3500,
    "leadTime": 10,
    "weight": { "value": 100, "unit": "lbs" },
    "status": "Active",
    "lastUpdated": "2026-01-15",
    "description": "Integrated workbench surface with tool storage for field service technicians.",
    "manufacturer": "EAVX"
  },
  {
    "id": "opt-upfit-dry-cleaning",
    "optionName": "Dry Cleaning Hanging Rod System",
    "category": "Interior",
    "compatibleBodies": ["Standard Box"],
    "price": 1500,
    "leadTime": 8,
    "weight": { "value": 45, "unit": "lbs" },
    "status": "Active",
    "lastUpdated": "2026-01-15",
    "description": "Garment hanging rod system for dry cleaning pickup and delivery fleets.",
    "manufacturer": "EAVX"
  },
  {
    "id": "opt-upfit-drawer",
    "optionName": "Drawer System",
    "category": "Interior",
    "compatibleBodies": ["Standard Box"],
    "price": 2000,
    "leadTime": 8,
    "weight": { "value": 60, "unit": "lbs" },
    "status": "Active",
    "lastUpdated": "2026-01-15",
    "description": "Modular drawer system for organized parts and small item storage.",
    "manufacturer": "EAVX"
  },
  {
    "id": "opt-shelving-grocery",
    "optionName": "Grocery Delivery Shelving",
    "category": "Interior",
    "compatibleBodies": ["Climate Conditioned"],
    "price": 2000,
    "leadTime": 10,
    "weight": { "value": 50, "unit": "lbs" },
    "status": "Active",
    "lastUpdated": "2026-01-15",
    "description": "Adjustable shelving system for totes and bags. Designed for organized grocery delivery operations.",
    "manufacturer": "EAVX"
  },
  {
    "id": "opt-shelving-bulk",
    "optionName": "Bulk Storage (Open Floor)",
    "category": "Interior",
    "compatibleBodies": ["Climate Conditioned"],
    "price": 0,
    "leadTime": 10,
    "weight": { "value": 0, "unit": "lbs" },
    "status": "Active",
    "lastUpdated": "2026-01-15",
    "description": "Open floor plan for pallet or bulk delivery. No shelving installed.",
    "manufacturer": "EAVX"
  },
  {
    "id": "opt-refrig-single",
    "optionName": "Single-Zone Chilled",
    "category": "Electrical",
    "compatibleBodies": ["Climate Conditioned"],
    "price": 5000,
    "leadTime": 12,
    "weight": { "value": 120, "unit": "lbs" },
    "status": "Active",
    "lastUpdated": "2026-01-15",
    "description": "Single-zone refrigeration unit maintaining 33-41\u00b0F for fresh produce and dairy.",
    "manufacturer": "EAVX"
  },
  {
    "id": "opt-refrig-dual",
    "optionName": "Dual-Zone (Chilled + Frozen)",
    "category": "Electrical",
    "compatibleBodies": ["Climate Conditioned"],
    "price": 7500,
    "leadTime": 14,
    "weight": { "value": 150, "unit": "lbs" },
    "status": "Active",
    "lastUpdated": "2026-01-15",
    "description": "Dual-zone system with independent chilled (33-41\u00b0F) and frozen (-10 to 0\u00b0F) compartments.",
    "manufacturer": "EAVX"
  },
  {
    "id": "opt-ki-cafe",
    "optionName": "Coffee/Caf\u00e9 Setup",
    "category": "Interior",
    "compatibleBodies": ["Kiosk"],
    "price": 5000,
    "leadTime": 12,
    "weight": { "value": 120, "unit": "lbs" },
    "status": "Active",
    "lastUpdated": "2026-01-15",
    "description": "Complete caf\u00e9 interior with espresso machine mounting, counter space, sink, and storage.",
    "manufacturer": "EAVX"
  },
  {
    "id": "opt-ki-merch",
    "optionName": "Merchandise Display",
    "category": "Interior",
    "compatibleBodies": ["Kiosk"],
    "price": 3500,
    "leadTime": 10,
    "weight": { "value": 80, "unit": "lbs" },
    "status": "Active",
    "lastUpdated": "2026-01-15",
    "description": "Retail display shelving with product lighting and lockable storage.",
    "manufacturer": "EAVX"
  },
  {
    "id": "opt-ki-service",
    "optionName": "Service Body Layout",
    "category": "Interior",
    "compatibleBodies": ["Kiosk"],
    "price": 3500,
    "leadTime": 10,
    "weight": { "value": 90, "unit": "lbs" },
    "status": "Active",
    "lastUpdated": "2026-01-15",
    "description": "Service-oriented interior layout with workbench and tool organization.",
    "manufacturer": "EAVX"
  },
  {
    "id": "opt-paint-white",
    "optionName": "White (Standard)",
    "category": "Exterior",
    "compatibleBodies": ["Standard Box", "Climate Conditioned", "Flat Bed", "Kiosk"],
    "price": 0,
    "leadTime": 0,
    "weight": { "value": 0, "unit": "lbs" },
    "status": "Active",
    "lastUpdated": "2026-01-15",
    "description": "Standard factory white paint.",
    "manufacturer": "EAVX"
  },
  {
    "id": "opt-paint-black",
    "optionName": "Black",
    "category": "Exterior",
    "compatibleBodies": ["Standard Box", "Climate Conditioned", "Flat Bed", "Kiosk"],
    "price": 500,
    "leadTime": 2,
    "weight": { "value": 0, "unit": "lbs" },
    "status": "Active",
    "lastUpdated": "2026-01-15",
    "description": "Premium black paint finish.",
    "manufacturer": "EAVX"
  },
  {
    "id": "opt-paint-custom",
    "optionName": "Custom Color",
    "category": "Exterior",
    "compatibleBodies": ["Standard Box", "Climate Conditioned", "Flat Bed", "Kiosk"],
    "price": 1500,
    "leadTime": 4,
    "weight": { "value": 0, "unit": "lbs" },
    "status": "Active",
    "lastUpdated": "2026-01-15",
    "description": "Custom paint-to-sample color matching.",
    "manufacturer": "EAVX"
  },
  {
    "id": "opt-charger-l2",
    "optionName": "Level 2 AC Charger (7.2 kW)",
    "category": "Electrical",
    "compatibleBodies": ["Standard Box", "Climate Conditioned", "Flat Bed", "Kiosk"],
    "price": 800,
    "leadTime": 4,
    "weight": { "value": 15, "unit": "lbs" },
    "status": "Active",
    "lastUpdated": "2026-01-15",
    "description": "Standard Level 2 AC charging unit for overnight depot charging.",
    "manufacturer": "ChargePoint"
  },
  {
    "id": "opt-refrig-frozen",
    "optionName": "Single-Zone Frozen",
    "category": "Electrical",
    "compatibleBodies": ["Climate Conditioned"],
    "price": 5500,
    "leadTime": 12,
    "weight": { "value": 130, "unit": "lbs" },
    "status": "Active",
    "lastUpdated": "2026-01-15",
    "description": "Single-zone freezer unit maintaining -10 to 0\u00b0F for frozen goods delivery.",
    "manufacturer": "EAVX"
  },
  {
    "id": "opt-ki-drawers",
    "optionName": "Under-Counter Drawers",
    "category": "Interior",
    "compatibleBodies": ["Kiosk"],
    "price": 1500,
    "leadTime": 8,
    "weight": { "value": 40, "unit": "lbs" },
    "status": "Active",
    "lastUpdated": "2026-01-15",
    "description": "Under-counter drawer storage for kiosk body configurations.",
    "manufacturer": "EAVX"
  },
  {
    "id": "opt-ki-cabinets",
    "optionName": "Overhead Storage Cabinets",
    "category": "Interior",
    "compatibleBodies": ["Kiosk"],
    "price": 1200,
    "leadTime": 8,
    "weight": { "value": 35, "unit": "lbs" },
    "status": "Active",
    "lastUpdated": "2026-01-15",
    "description": "Overhead storage cabinets for kiosk body configurations.",
    "manufacturer": "EAVX"
  },
  {
    "id": "opt-fb-stake",
    "optionName": "Stake Body",
    "category": "Exterior",
    "compatibleBodies": ["Flat Bed"],
    "price": 3000,
    "leadTime": 8,
    "weight": { "value": 200, "unit": "lbs" },
    "status": "Active",
    "lastUpdated": "2026-01-15",
    "description": "Stake body with removable side panels for bulk material transport.",
    "manufacturer": "EAVX"
  },
  {
    "id": "opt-fb-refuse",
    "optionName": "Refuse Body",
    "category": "Exterior",
    "compatibleBodies": ["Flat Bed"],
    "price": 5000,
    "leadTime": 10,
    "weight": { "value": 300, "unit": "lbs" },
    "status": "Active",
    "lastUpdated": "2026-01-15",
    "description": "Refuse collection body for waste management operations.",
    "manufacturer": "EAVX"
  },
  {
    "id": "opt-fb-service",
    "optionName": "Service Body",
    "category": "Exterior",
    "compatibleBodies": ["Flat Bed"],
    "price": 4000,
    "leadTime": 10,
    "weight": { "value": 250, "unit": "lbs" },
    "status": "Active",
    "lastUpdated": "2026-01-15",
    "description": "Service body with compartmentalized storage for field service operations.",
    "manufacturer": "EAVX"
  },
  {
    "id": "opt-fb-dump",
    "optionName": "Dump Body",
    "category": "Exterior",
    "compatibleBodies": ["Flat Bed"],
    "price": 4500,
    "leadTime": 10,
    "weight": { "value": 280, "unit": "lbs" },
    "status": "Active",
    "lastUpdated": "2026-01-15",
    "description": "Hydraulic dump body for construction and landscaping material transport.",
    "manufacturer": "EAVX"
  },
  {
    "id": "opt-charger-dc",
    "optionName": "DC Fast Charger (50 kW)",
    "category": "Electrical",
    "compatibleBodies": ["Standard Box", "Climate Conditioned", "Flat Bed", "Kiosk"],
    "price": 3500,
    "leadTime": 6,
    "weight": { "value": 45, "unit": "lbs" },
    "status": "Active",
    "lastUpdated": "2026-01-15",
    "description": "DC fast charging unit enabling rapid charging at commercial depots. 80% charge in under 1 hour.",
    "manufacturer": "ChargePoint"
  }
]
